encryptlib/__init__.py
encryptlib/core.py
encryptlib/exceptions.py
encryptlib/utils.py
en_encrypt-1.0.1.1.dist-info/METADATA
en_encrypt-1.0.1.1.dist-info/WHEEL
en_encrypt-1.0.1.1.dist-info/licenses/LICENSE
en_encrypt-1.0.1.1.dist-info/RECORD
