Metadata-Version: 2.4
Name: EN-ENcrypt
Version: 1.0.1.1
Summary: A matrix-based encryption library developed for TUBITAK 2204-a
Project-URL: Homepage, https://github.com/TheBruh141/89crypt
Project-URL: Repository, https://github.com/TheBruh141/89crypt
Project-URL: Documentation, https://89crypt.readthedocs.io
Project-URL: Bug_Tracker, https://github.com/TheBruh141/89crypt/issues
Author-email: Bruh141 <141bruh@gmail.com>
License: GNU GPLv3
License-File: LICENSE
Classifier: Development Status :: 4 - Beta
Classifier: Intended Audience :: Education
Classifier: License :: OSI Approved :: GNU General Public License v3 (GPLv3)
Classifier: Operating System :: OS Independent
Classifier: Programming Language :: Python :: 3
Classifier: Programming Language :: Python :: 3.13
Classifier: Topic :: Security :: Cryptography
Requires-Python: >=3.8
Requires-Dist: mpmath~=1.3.0
Requires-Dist: numpy~=2.2.1
Provides-Extra: dev
Requires-Dist: black>=24.1.0; extra == 'dev'
Requires-Dist: isort>=5.13.0; extra == 'dev'
Requires-Dist: mypy>=1.8.0; extra == 'dev'
Requires-Dist: pytest-cov>=4.1.0; extra == 'dev'
Requires-Dist: pytest>=8.0.0; extra == 'dev'
Provides-Extra: docs
Requires-Dist: myst-parser>=2.0.0; extra == 'docs'
Requires-Dist: sphinx-autodoc-typehints>=1.25.0; extra == 'docs'
Requires-Dist: sphinx-book-theme>=1.1.3; extra == 'docs'
Requires-Dist: sphinx>=7.2.0; extra == 'docs'
